vhsh/__init__.py
vhsh/__main__.py
vhsh/midi_mappings/korg_nanoKONTROL2.nktrl2_data
vhsh/midi_mappings/korg_nanoKONTROL2.toml
vhsh-0.1.2.dist-info/licenses/LICENSE
vhsh-0.1.2.dist-info/WHEEL
vhsh-0.1.2.dist-info/entry_points.txt
vhsh-0.1.2.dist-info/METADATA
vhsh-0.1.2.dist-info/RECORD
