Metadata-Version: 2.4
Name: vhsh
Version: 0.1.2
Summary: Video Home Shader: A demo tool for digitally assisted analog vjaying
Author: Philipp Stephan
Author-email: Philipp Stephan <mail@philippstephan.de>
License-Expression: MIT
License-File: LICENSE
Classifier: Programming Language :: Python :: 3
Classifier: Operating System :: OS Independent
Classifier: Development Status :: 4 - Beta
Classifier: Environment :: GPU
Classifier: Topic :: Artistic Software
Classifier: Topic :: Multimedia :: Graphics :: 3D Rendering
Requires-Dist: pyopengl
Requires-Dist: glfw
Requires-Dist: imgui[glfw]
Requires-Dist: numpy
Requires-Dist: watchfiles
Requires-Dist: vhsh[midi,audio] ; extra == 'all'
Requires-Dist: pyaudio ; extra == 'audio'
Requires-Dist: ruff ; extra == 'dev'
Requires-Dist: pyright ; extra == 'dev'
Requires-Dist: pyimgui-stubs ; extra == 'dev'
Requires-Dist: mido[ports-rtmidi] ; extra == 'midi'
Requires-Python: ==3.12.*
Project-URL: Homepage, https://github.com/phistep/vhsh
Project-URL: Issues, https://github.com/phistep/vhsh/issues
Provides-Extra: all
Provides-Extra: audio
Provides-Extra: dev
Provides-Extra: midi
